nagiosplugin/__init__.py
nagiosplugin/check.py
nagiosplugin/compat.py
nagiosplugin/context.py
nagiosplugin/cookie.py
nagiosplugin/error.py
nagiosplugin/logtail.py
nagiosplugin/metric.py
nagiosplugin/multiarg.py
nagiosplugin/output.py
nagiosplugin/performance.py
nagiosplugin/range.py
nagiosplugin/resource.py
nagiosplugin/result.py
nagiosplugin/runtime.py
nagiosplugin/state.py
nagiosplugin/summary.py
nagiosplugin/version.py
nagiosplugin/examples/__init__.py
nagiosplugin/examples/check_haproxy_log.py
nagiosplugin/examples/check_load.py
nagiosplugin/examples/check_users.py
nagiosplugin/examples/check_world.py
nagiosplugin/platform/__init__.py
nagiosplugin/platform/nt.py
nagiosplugin/platform/posix.py
nagiosplugin-1.4.0.dist-info/licenses/LICENSE.txt
nagiosplugin-1.4.0.dist-info/METADATA
nagiosplugin-1.4.0.dist-info/WHEEL
nagiosplugin-1.4.0.dist-info/top_level.txt
nagiosplugin-1.4.0.dist-info/RECORD
