Metadata-Version: 2.4
Name: nagiosplugin
Version: 1.4.0
Summary: Class library for writing Nagios (Icinga) plugins
Home-page: https://nagiosplugin.readthedocs.io/
Download-URL: https://pypi.org/project/nagiosplugin/
Author: Matthew Pounsett
Author-email: matt@conundrum.com
License: ZPL-2.1
Project-URL: nagiosplugin source, https://github.com/mpounsett/nagiosplugin
Project-URL: nagiosplugin issues, https://github.com/mpounsett/nagiosplugin/issues
Keywords: Nagios Icinga plugin check monitoring
Classifier: Development Status :: 5 - Production/Stable
Classifier: Environment :: Plugins
Classifier: Intended Audience :: Developers
Classifier: Intended Audience :: System Administrators
Classifier: License :: OSI Approved :: Zope Public License
Classifier: Operating System :: Microsoft :: Windows
Classifier: Operating System :: POSIX
Classifier: Programming Language :: Python :: 2.7
Classifier: Programming Language :: Python :: 3.7
Classifier: Programming Language :: Python :: 3.8
Classifier: Programming Language :: Python :: 3.9
Classifier: Programming Language :: Python :: 3.10
Classifier: Programming Language :: Python :: 3.11
Classifier: Programming Language :: Python :: 3.12
Classifier: Programming Language :: Python :: 3.13
Classifier: Topic :: Software Development :: Libraries :: Python Modules
Classifier: Topic :: System :: Monitoring
License-File: LICENSE.txt
Dynamic: author
Dynamic: author-email
Dynamic: classifier
Dynamic: description
Dynamic: download-url
Dynamic: home-page
Dynamic: keywords
Dynamic: license
Dynamic: license-file
Dynamic: project-url
Dynamic: summary
